sqldictalchem/__init__.py
sqldictalchem/classes.py
sqldictalchem/constants.py
sqldictalchem/errors.py
sqldictalchem/utils.py
sqldictalchem/tests/__init__.py
sqldictalchem/tests/test_asdict.py
sqldictalchem/tests/test_fromdict.py
sqldictalchem/tests/test_utils.py
sqldictalchem-0.1.1.dist-info/LICENSE
sqldictalchem-0.1.1.dist-info/METADATA
sqldictalchem-0.1.1.dist-info/WHEEL
sqldictalchem-0.1.1.dist-info/top_level.txt
sqldictalchem-0.1.1.dist-info/RECORD
